fracmechfactors/LEFMfactor.py
fracmechfactors/__init__.py
fracmechfact-0.0.12.dist-info/LICENSE
fracmechfact-0.0.12.dist-info/METADATA
fracmechfact-0.0.12.dist-info/WHEEL
fracmechfact-0.0.12.dist-info/top_level.txt
fracmechfact-0.0.12.dist-info/RECORD
