Metadata-Version: 2.1
Name: fracmechfact
Version: 0.0.12
Summary: This is a package to extract the Non-dimensional factors of fracture mechanics.
Author: Hrushikesh Sahasrabuddhe
Author-email: <sahasrabuddhehrushi.99@gmail.com>
Keywords: python,fracture mechanics,geometric factor
Classifier: Development Status :: 1 - Planning
Classifier: Intended Audience :: Developers
Classifier: Programming Language :: Python :: 3
Classifier: Operating System :: Unix
Classifier: Operating System :: MacOS :: MacOS X
Classifier: Operating System :: Microsoft :: Windows
License-File: LICENSE
